autodbconnect/__init__.py
autodbconnect/mongo_crud.py
autodbconnect-0.0.1.dist-info/LICENSE
autodbconnect-0.0.1.dist-info/METADATA
autodbconnect-0.0.1.dist-info/WHEEL
autodbconnect-0.0.1.dist-info/top_level.txt
autodbconnect-0.0.1.dist-info/RECORD
